tacotron2_model/__init__.py
tacotron2_model/audio_processing.py
tacotron2_model/collate.py
tacotron2_model/layers.py
tacotron2_model/loss.py
tacotron2_model/model.py
tacotron2_model/stft.py
tacotron2_model/utils.py
tacotron2_model-0.2.4.dist-info/LICENSE
tacotron2_model-0.2.4.dist-info/METADATA
tacotron2_model-0.2.4.dist-info/WHEEL
tacotron2_model-0.2.4.dist-info/top_level.txt
tacotron2_model-0.2.4.dist-info/RECORD
