Metadata-Version: 2.1
Name: tacotron2-model
Version: 0.2.4
Summary: A PyPI port of the NVIDIA Tacotron2 model
Home-page: https://github.com/BenAAndrew/tacotron2-model
Author: Ben Andrew
Author-email: benandrew89@gmail.com
License: UNKNOWN
Platform: UNKNOWN
Classifier: Programming Language :: Python :: 3
Classifier: License :: OSI Approved :: BSD License
Classifier: Operating System :: OS Independent
Requires-Python: >=3.5
